tk_steroids/__init__.py
tk_steroids/colors.py
tk_steroids/datamanager.py
tk_steroids/dialogs.py
tk_steroids/elements.py
tk_steroids/imagefeed.py
tk_steroids/matplotlib.py
tk_steroids/menumaker.py
tk_steroids/routines.py
tk_steroids/settings.py
tk_steroids/version.py
tk_steroids-0.8.1.dist-info/licenses/LICENSE
tk_steroids-0.8.1.dist-info/METADATA
tk_steroids-0.8.1.dist-info/WHEEL
tk_steroids-0.8.1.dist-info/top_level.txt
tk_steroids-0.8.1.dist-info/RECORD
