Metadata-Version: 2.4
Name: tk-steroids
Version: 0.8.1
Summary: A collection of custom tkinter bits
Home-page: https://github.com/musaprog/tk-steroids
Author: Joni Kemppainen
Author-email: joni.kemppainen@windowslive.com
Classifier: Programming Language :: Python :: 3
Classifier: License :: OSI Approved :: GNU General Public License v3 (GPLv3)
Classifier: Operating System :: OS Independent
Requires-Python: >=3.6
License-File: LICENSE
Requires-Dist: Pillow
Requires-Dist: numpy
Requires-Dist: matplotlib
Dynamic: author
Dynamic: author-email
Dynamic: classifier
Dynamic: description
Dynamic: description-content-type
Dynamic: home-page
Dynamic: license-file
Dynamic: requires-dist
Dynamic: requires-python
Dynamic: summary
